secman/__init__.py
secman/__main__.py
secman/easysecrets.py
secman/secman.py
secman/secretsmanager.py
secman/libs/__init__.py
secman/libs/crypto_utils.py
secman-0.2.0.dist-info/LICENSE
secman-0.2.0.dist-info/METADATA
secman-0.2.0.dist-info/WHEEL
secman-0.2.0.dist-info/top_level.txt
secman-0.2.0.dist-info/RECORD
