Metadata-Version: 2.1
Name: secman
Version: 0.2.0
Summary: Secrets Manager. An easy and safe way to manage your project secrets.
Author-email: EduardoRE <rodested@yahoo.com>
License: AGPL-3.0-only
Project-URL: Homepage, https://github.com/rodested/secman
Project-URL: Issues, https://github.com/rodested/secman/issues
Requires-Python: >=3.10
License-File: LICENSE
Requires-Dist: requests >=2.32.3
Requires-Dist: cryptography >=42.0.8
